regressive_counter/hexa7seg.v
module hexa7seg (
    input [3:0] hexa,        // 4-bit input (hex digit)
    output reg [6:0] sseg    // 7-bit output for 7-segment display
);

    always @(*) begin
        case (hexa)
            4'b0000: sseg = 7'b1000000; // 0
            4'b0001: sseg = 7'b1111001; // 1
            4'b0010: sseg = 7'b0100100; // 2
            4'b0011: sseg = 7'b0110000; // 3
            4'b0100: sseg = 7'b0011001; // 4
            4'b0101: sseg = 7'b0010010; // 5
            4'b0110: sseg = 7'b0000010; // 6
            4'b0111: sseg = 7'b1111000; // 7
            4'b1000: sseg = 7'b0000000; // 8
            4'b1001: sseg = 7'b0010000; // 9
            4'b1010: sseg = 7'b0001000; // A
            4'b1011: sseg = 7'b0000011; // b
            4'b1100: sseg = 7'b1000110; // C
            4'b1101: sseg = 7'b0100001; // d
            4'b1110: sseg = 7'b0000110; // E
            4'b1111: sseg = 7'b0001110; // F
            default: sseg = 7'b1111111; // Invalid or unused input
        endcase
    end

endmodule

regressive_counter/one_second_counter.v
module one_second_counter (
	input clock,
	input reset,
	input start,
	output finished
);

integer one_second = 50_000_000; // testei no gtkwave com 4;
integer clock_counter = 0;

reg finished_detect = 1'b0;

always @(posedge clock) begin
	if (reset) begin
		clock_counter <= 0;
		finished_detect <= 1'b0;
	end else begin
		if (start) begin
			clock_counter <= clock_counter + 1;
			if (clock_counter == one_second - 1) begin //compensation
				clock_counter <= 0;
				finished_detect <= 1'b1;
			end else begin
				finished_detect <= 1'b0;
			end
		end
	end
end

assign finished = finished_detect;

endmodule

regressive_counter/regressive_counter.v
// Antes do start hex5_seconds_left deve mostrar seconds_period

module regressive_counter (
    input clock,
    input reset,
    input [3:0] seconds_period, // define o período de tempo
    input start,
    output [6:0] hex5_seconds_left, // mostrar qunato tempo falta
    output reg ledr9_finished
);

    reg [3:0] valor_atual;
    wire pulso_de_1s;

    one_second_counter contador (
        .clock(clock),
        .reset(reset),
        .start(start), // O contador de tempo só anda se start estiver alto
        .finished(pulso_de_1s)
    );

    hexa7seg display (
        .hexa(contagem_atual),
        .sseg(hex5_seconds_left)
    );

    always @(posedge clock) begin
        if (reset) begin
            contagem_atual <= seconds_period;
            ledr9_finished <= 1'b0;
        end 
        else if (start) begin
            if (pulso_de_1s) begin
                if (contagem_atual == 0) begin
                    contagem_atual <= seconds_period;
                    ledr9_finished <= 1'b0;
                end else begin
                    contagem_atual <= contagem_atual - 1;
                end
            end
            if (contagem_atual == 0) 
                ledr9_finished <= 1'b1;
            else 
                ledr9_finished <= 1'b0;  
        end
    end

endmodule

regressive_counter/tb_regressive.v
`timescale 1ns / 1ps

module tb_regressive;
    reg clock;
    reg reset;
    reg [3:0] seconds_period;
    reg start;

    wire [6:0] hex5_seconds_left;
    wire ledr9_finished;

    regressive_counter uut (
        .clock(clock), 
        .reset(reset), 
        .seconds_period(seconds_period), 
        .start(start), 
        .hex5_seconds_left(hex5_seconds_left), 
        .ledr9_finished(ledr9_finished)
    );

    always #10 clock = ~clock;

    initial begin
        $dumpfile("ondas.vcd");
        $dumpvars(0, tb_regressive);

        // Estado Inicial
        clock = 0;
        reset = 1;
        start = 0;
        seconds_period = 4'd5; // 5 segundos

        // Espera um pouco e solta o reset
        #20 reset = 0;

        // Inicia a contagem
        #20 start = 1;

        // Roda por tempo suficiente para ver a contagem chegar a 0 e reiniciar
        #600;

        // Teste de Pause
        start = 0;
        #100;
        start = 1;
        #200;

        $finish;
    end
endmodule

regressive_counter/ondas.vcd
$date
	Mon Feb 09 23:03:14 2026
$end
$version
	Icarus Verilog
$end
$timescale
	1ps
$end
$scope module tb_regressive $end
$var wire 1 ! ledr9_finished $end
$var wire 7 " hex5_seconds_left [6:0] $end
$var reg 1 # clock $end
$var reg 1 $ reset $end
$var reg 4 % seconds_period [3:0] $end
$var reg 1 & start $end
$scope module uut $end
$var wire 1 # clock $end
$var wire 1 $ reset $end
$var wire 4 ' seconds_period [3:0] $end
$var wire 1 & start $end
$var wire 1 ( pulso_de_1s $end
$var wire 7 ) hex5_seconds_left [6:0] $end
$var reg 1 ! ledr9_finished $end
$var reg 4 * valor_atual [3:0] $end
$scope module contador $end
$var wire 1 # clock $end
$var wire 1 ( finished $end
$var wire 1 $ reset $end
$var wire 1 & start $end
$var reg 1 + finished_detect $end
$var integer 32 , clock_counter [31:0] $end
$var integer 32 - one_second [31:0] $end
$upscope $end
$scope module display $end
$var wire 4 . hexa [3:0] $end
$var reg 7 / sseg [6:0] $end
$upscope $end
$upscope $end
$upscope $end
$enddefinitions $end
$comment Show the parameter values. $end
$dumpall
$end
#0
$dumpvars
bx /
bx .
b100 -
b0 ,
0+
bx *
bx )
0(
b101 '
0&
b101 %
1$
0#
bx "
x!
$end
#10000
b10010 "
b10010 )
b10010 /
0!
b101 *
b101 .
1#
#20000
0#
0$
#30000
1#
#40000
0#
1&
#50000
b1 ,
1#
#60000
0#
#70000
b10 ,
1#
#80000
0#
#90000
b11 ,
1#
#100000
0#
#110000
1(
1+
b0 ,
1#
#120000
0#
#130000
b11001 "
b11001 )
b11001 /
0(
0+
b1 ,
b100 *
b100 .
1#
#140000
0#
#150000
b10 ,
1#
#160000
0#
#170000
b11 ,
1#
#180000
0#
#190000
1(
1+
b0 ,
1#
#200000
0#
#210000
b110000 "
b110000 )
b110000 /
0(
0+
b1 ,
b11 *
b11 .
1#
#220000
0#
#230000
b10 ,
1#
#240000
0#
#250000
b11 ,
1#
#260000
0#
#270000
1(
1+
b0 ,
1#
#280000
0#
#290000
b100100 "
b100100 )
b100100 /
0(
0+
b1 ,
b10 *
b10 .
1#
#300000
0#
#310000
b10 ,
1#
#320000
0#
#330000
b11 ,
1#
#340000
0#
#350000
1(
1+
b0 ,
1#
#360000
0#
#370000
b1111001 "
b1111001 )
b1111001 /
0(
0+
b1 ,
b1 *
b1 .
1#
#380000
0#
#390000
b10 ,
1#
#400000
0#
#410000
b11 ,
1#
#420000
0#
#430000
1(
1+
b0 ,
1#
#440000
0#
#450000
b1000000 "
b1000000 )
b1000000 /
0(
0+
b1 ,
b0 *
b0 .
1#
#460000
0#
#470000
1!
b10 ,
1#
#480000
0#
#490000
b11 ,
1#
#500000
0#
#510000
1(
1+
b0 ,
1#
#520000
0#
#530000
b10010 "
b10010 )
b10010 /
0(
0+
b1 ,
1!
b101 *
b101 .
1#
#540000
0#
#550000
0!
b10 ,
1#
#560000
0#
#570000
b11 ,
1#
#580000
0#
#590000
1(
1+
b0 ,
1#
#600000
0#
#610000
b11001 "
b11001 )
b11001 /
0(
0+
b1 ,
b100 *
b100 .
1#
#620000
0#
#630000
b10 ,
1#
#640000
0#
0&
#650000
1#
#660000
0#
#670000
1#
#680000
0#
#690000
1#
#700000
0#
#710000
1#
#720000
0#
#730000
1#
#740000
0#
1&
#750000
b11 ,
1#
#760000
0#
#770000
1(
1+
b0 ,
1#
#780000
0#
#790000
b110000 "
b110000 )
b110000 /
b11 *
b11 .
0(
0+
b1 ,
1#
#800000
0#
#810000
b10 ,
1#
#820000
0#
#830000
b11 ,
1#
#840000
0#
#850000
1(
1+
b0 ,
1#
#860000
0#
#870000
b100100 "
b100100 )
b100100 /
b10 *
b10 .
0(
0+
b1 ,
1#
#880000
0#
#890000
b10 ,
1#
#900000
0#
#910000
b11 ,
1#
#920000
0#
#930000
1(
1+
b0 ,
1#
